LICENSE.txt
MANIFEST.in
setup.cfg
setup.py
bin/pyxapp
pyxley/__init__.py
pyxley/react_template.py
pyxley/router.py
pyxley/ui.py
pyxley.egg-info/PKG-INFO
pyxley.egg-info/SOURCES.txt
pyxley.egg-info/dependency_links.txt
pyxley.egg-info/requires.txt
pyxley.egg-info/top_level.txt
pyxley/assets/bundle.js
pyxley/assets/index.html
pyxley/assets/main.css
pyxley/charts/__init__.py
pyxley/charts/charts.py
pyxley/charts/datamaps/__init__.py
pyxley/charts/datamaps/datamaps.py
pyxley/charts/datatables/__init__.py
pyxley/charts/datatables/datatable.py
pyxley/charts/mg/__init__.py
pyxley/charts/mg/axes.py
pyxley/charts/mg/barchart.py
pyxley/charts/mg/figure.py
pyxley/charts/mg/graphic.py
pyxley/charts/mg/histogram.py
pyxley/charts/mg/layout.py
pyxley/charts/mg/line_chart.py
pyxley/charts/mg/mg.py
pyxley/charts/mg/scatter_plot.py
pyxley/charts/nvd3/__init__.py
pyxley/charts/nvd3/nvd3.py
pyxley/charts/nvd3/pie_chart.py
pyxley/charts/nvd3/two_axis_focus.py
pyxley/charts/plotly/__init__.py
pyxley/charts/plotly/base.py
pyxley/filters/__init__.py
pyxley/filters/filters.py
pyxley/utils/__init__.py
pyxley/utils/flask_helper.py
pyxley/utils/npm.py
pyxley/utils/webpack.py