Metadata-Version: 1.1
Name: pyxley
Version: 0.1.0
Summary: Python tools for building Flask-based web applications
Home-page: https://github.com/stitchfix/pyxley
Author: Nicholas Kridler
Author-email: nmkridler@gmail.com
License: MIT
Keywords: pyreact,flask
Platform: UNKNOWN
Classifier: Intended Audience :: Developers
